binaryrepr.py
binaryrepr-0.19.dist-info/LICENSE
binaryrepr-0.19.dist-info/METADATA
binaryrepr-0.19.dist-info/WHEEL
binaryrepr-0.19.dist-info/entry_points.txt
binaryrepr-0.19.dist-info/top_level.txt
binaryrepr-0.19.dist-info/RECORD
